pylonparser/__init__.py
pylonparser/matches.py
pylonparser/schedules.py
pylonparser/scraper.py
pylonparser-0.5.1.dist-info/LICENSE
pylonparser-0.5.1.dist-info/METADATA
pylonparser-0.5.1.dist-info/WHEEL
pylonparser-0.5.1.dist-info/RECORD
